[
    {
        "id": 4,
        "author": "chenxq",
        "title": "方沟通然",
        "summary": "广泛认同个人",
        "create_by": "2019-03-27 15:16:17",
        "modified_by": "2019-03-27 15:16:17",
        "content": "重复感染他也人"
    },
    {
        "id": 5,
        "author": "chenxq",
        "title": "V》nhg；u以方便v能力和官方；，哪怕【一套房，和b",
        "summary": "可促进面部v弄i应该分开今后try【i考核表v；看美女有【‘投个票会更明白v美女平衡各方",
        "create_by": "2019-04-02 10:39:29",
        "modified_by": "2019-04-02 10:39:29",
        "content": "风格和加内特翻译看见美女表面划过附近有静安大火附属卡红色反扑额外三回复觉得你夫君奥克苏瓦而非角色的画风讲究的是几点睡啊防火卷帘卡和尚房价跌幅扩大解放阿斯顿回复就撒了回复\n你觉得双方距离喀什发的链接而我i\n的那份垃圾啊开始的覅破二级台风\n框架搭建诺福克例如覅偶尔怕人家覅的\n#### v看见你们电视机分厘卡女郎单身妇女\ndjsfoiejmc.nv虚空假面v付款\n++反对v看电视了JFK男方女方++\n![3b63c6921668aa3d5d17736ea1a33cc5.jpeg](/server/images/98527d460e494f31942eb133e380b317.jpeg)"
    },
    {
        "id": 6,
        "author": "chenxq",
        "title": "sdfer",
        "summary": "dsfewf",
        "create_by": "2019-04-08 15:04:07",
        "modified_by": "2019-04-08 15:04:07",
        "content": "dsff"
    }
]